onelab/__init__.py
onelab/podcast.py
onelab/schema.py
onelab/tts.py
onelab/sample/alex.wav
onelab/sample/charlie.wav
onelab/sample/dwight.wav
onelab/sample/emilia.wav
onelab/sample/erin.wav
onelab/sample/frasier.wav
onelab/sample/helen.wav
onelab/sample/jerry.wav
onelab/sample/richard.wav
onelab/sample/samantha.wav
onelab_tts-0.2.0.dist-info/METADATA
onelab_tts-0.2.0.dist-info/WHEEL
onelab_tts-0.2.0.dist-info/top_level.txt
onelab_tts-0.2.0.dist-info/RECORD
