Metadata-Version: 2.4
Name: onelab-tts
Version: 0.2.0
Summary: A Text-to-Speech and Podcast generation library using Chatterbox Turbo TTS
Author-email: OneLab Team <satadeep.dasgupta@brainiuminfotech.com>
Project-URL: Homepage, https://github.com/satadeep3927/onelab
Project-URL: Bug Tracker, https://github.com/satadeep3927/onelab/issues
Classifier: Programming Language :: Python :: 3
Classifier: License :: OSI Approved :: MIT License
Classifier: Operating System :: OS Independent
Requires-Python: <3.12,>=3.8
Requires-Dist: torch
Requires-Dist: torchaudio
Requires-Dist: chatterbox-tts
Requires-Dist: pydantic
